{
  "config": {
    "ckpt": "results/scaled/base_model_fp16.pt",
    "output": "results/scaled/exp_scale_bridge_ablation.json",
    "context_lengths": [
      1024,
      2048,
      4096
    ],
    "n_samples": 48,
    "seeds": [
      42,
      43,
      44
    ],
    "device": "mps",
    "model_cfg": {
      "dim": 192,
      "depth": 6,
      "vocab_size": 4096,
      "max_len": 8192,
      "num_classes": 64,
      "heads": 6,
      "k_frac": 0.25,
      "episodic_slots": 32,
      "episodic_write_frac": 0.05,
      "mlp_ratio": 4.0,
      "use_scale_bridge": true,
      "ssm_bits": 2,
      "attn_bits": 4,
      "mem_bits": 8,
      "ram_budget_fraction": 0.75
    }
  },
  "runs": {
    "42": {
      "with_bridge": {
        "per_ctx": {
          "1024": {
            "niah_single": 0.5,
            "niah_multi_key": 0.14583333333333334,
            "multi_task": 0.48936170212765956,
            "eval_time_s": 6.566772166988812
          },
          "2048": {
            "niah_single": 0.5,
            "niah_multi_key": 0.16666666666666666,
            "multi_task": 0.3617021276595745,
            "eval_time_s": 6.517129875021055
          },
          "4096": {
            "niah_single": 0.4583333333333333,
            "niah_multi_key": 0.125,
            "multi_task": 0.3723404255319149,
            "eval_time_s": 17.11775470909197
          }
        }
      },
      "no_bridge": {
        "per_ctx": {
          "1024": {
            "niah_single": 0.041666666666666664,
            "niah_multi_key": 0.0,
            "multi_task": 0.031914893617021274,
            "eval_time_s": 5.924521000008099
          },
          "2048": {
            "niah_single": 0.041666666666666664,
            "niah_multi_key": 0.0,
            "multi_task": 0.031914893617021274,
            "eval_time_s": 5.752004583016969
          },
          "4096": {
            "niah_single": 0.041666666666666664,
            "niah_multi_key": 0.0,
            "multi_task": 0.031914893617021274,
            "eval_time_s": 16.178239541011862
          }
        }
      }
    },
    "43": {
      "with_bridge": {
        "per_ctx": {
          "1024": {
            "niah_single": 0.7083333333333334,
            "niah_multi_key": 0.041666666666666664,
            "multi_task": 0.4148936170212766,
            "eval_time_s": 7.772512624971569
          },
          "2048": {
            "niah_single": 0.625,
            "niah_multi_key": 0.08333333333333333,
            "multi_task": 0.40425531914893614,
            "eval_time_s": 9.048836666974239
          },
          "4096": {
            "niah_single": 0.4583333333333333,
            "niah_multi_key": 0.041666666666666664,
            "multi_task": 0.3617021276595745,
            "eval_time_s": 50.295095082954504
          }
        }
      },
      "no_bridge": {
        "per_ctx": {
          "1024": {
            "niah_single": 0.020833333333333332,
            "niah_multi_key": 0.020833333333333332,
            "multi_task": 0.010638297872340425,
            "eval_time_s": 12.562787542003207
          },
          "2048": {
            "niah_single": 0.020833333333333332,
            "niah_multi_key": 0.020833333333333332,
            "multi_task": 0.010638297872340425,
            "eval_time_s": 10.218405791907571
          },
          "4096": {
            "niah_single": 0.020833333333333332,
            "niah_multi_key": 0.020833333333333332,
            "multi_task": 0.010638297872340425,
            "eval_time_s": 25.867741915979423
          }
        }
      }
    },
    "44": {
      "with_bridge": {
        "per_ctx": {
          "1024": {
            "niah_single": 0.6458333333333334,
            "niah_multi_key": 0.0625,
            "multi_task": 0.425531914893617,
            "eval_time_s": 9.85697604098823
          },
          "2048": {
            "niah_single": 0.3958333333333333,
            "niah_multi_key": 0.0625,
            "multi_task": 0.4148936170212766,
            "eval_time_s": 10.08432762499433
          },
          "4096": {
            "niah_single": 0.3958333333333333,
            "niah_multi_key": 0.16666666666666666,
            "multi_task": 0.3723404255319149,
            "eval_time_s": 28.005376041983254
          }
        }
      },
      "no_bridge": {
        "per_ctx": {
          "1024": {
            "niah_single": 0.020833333333333332,
            "niah_multi_key": 0.0625,
            "multi_task": 0.031914893617021274,
            "eval_time_s": 9.455060999956913
          },
          "2048": {
            "niah_single": 0.020833333333333332,
            "niah_multi_key": 0.0625,
            "multi_task": 0.031914893617021274,
            "eval_time_s": 8.971796958008781
          },
          "4096": {
            "niah_single": 0.020833333333333332,
            "niah_multi_key": 0.0625,
            "multi_task": 0.031914893617021274,
            "eval_time_s": 26.247550916974433
          }
        }
      }
    }
  },
  "summary": {
    "with_bridge": {
      "1024": {
        "niah_single": {
          "mean": 0.6180555555555557,
          "std": 0.1069083633218101,
          "vals": [
            0.5,
            0.7083333333333334,
            0.6458333333333334
          ]
        },
        "niah_multi_key": {
          "mean": 0.08333333333333333,
          "std": 0.05511981898051231,
          "vals": [
            0.14583333333333334,
            0.041666666666666664,
            0.0625
          ]
        },
        "multi_task": {
          "mean": 0.4432624113475177,
          "std": 0.04027594571489555,
          "vals": [
            0.48936170212765956,
            0.4148936170212766,
            0.425531914893617
          ]
        }
      },
      "2048": {
        "niah_single": {
          "mean": 0.5069444444444444,
          "std": 0.11474105306846047,
          "vals": [
            0.5,
            0.625,
            0.3958333333333333
          ]
        },
        "niah_multi_key": {
          "mean": 0.10416666666666667,
          "std": 0.0551198189805123,
          "vals": [
            0.16666666666666666,
            0.08333333333333333,
            0.0625
          ]
        },
        "multi_task": {
          "mean": 0.39361702127659576,
          "std": 0.028146290543240304,
          "vals": [
            0.3617021276595745,
            0.40425531914893614,
            0.4148936170212766
          ]
        }
      },
      "4096": {
        "niah_single": {
          "mean": 0.4375,
          "std": 0.036084391824351615,
          "vals": [
            0.4583333333333333,
            0.4583333333333333,
            0.3958333333333333
          ]
        },
        "niah_multi_key": {
          "mean": 0.1111111111111111,
          "std": 0.06364688465216445,
          "vals": [
            0.125,
            0.041666666666666664,
            0.16666666666666666
          ]
        },
        "multi_task": {
          "mean": 0.3687943262411348,
          "std": 0.006142024140315144,
          "vals": [
            0.3723404255319149,
            0.3617021276595745,
            0.3723404255319149
          ]
        }
      }
    },
    "no_bridge": {
      "1024": {
        "niah_single": {
          "mean": 0.027777777777777776,
          "std": 0.012028130608117204,
          "vals": [
            0.041666666666666664,
            0.020833333333333332,
            0.020833333333333332
          ]
        },
        "niah_multi_key": {
          "mean": 0.027777777777777776,
          "std": 0.031823442326082224,
          "vals": [
            0.0,
            0.020833333333333332,
            0.0625
          ]
        },
        "multi_task": {
          "mean": 0.02482269503546099,
          "std": 0.012284048280630334,
          "vals": [
            0.031914893617021274,
            0.010638297872340425,
            0.031914893617021274
          ]
        }
      },
      "2048": {
        "niah_single": {
          "mean": 0.027777777777777776,
          "std": 0.012028130608117204,
          "vals": [
            0.041666666666666664,
            0.020833333333333332,
            0.020833333333333332
          ]
        },
        "niah_multi_key": {
          "mean": 0.027777777777777776,
          "std": 0.031823442326082224,
          "vals": [
            0.0,
            0.020833333333333332,
            0.0625
          ]
        },
        "multi_task": {
          "mean": 0.02482269503546099,
          "std": 0.012284048280630334,
          "vals": [
            0.031914893617021274,
            0.010638297872340425,
            0.031914893617021274
          ]
        }
      },
      "4096": {
        "niah_single": {
          "mean": 0.027777777777777776,
          "std": 0.012028130608117204,
          "vals": [
            0.041666666666666664,
            0.020833333333333332,
            0.020833333333333332
          ]
        },
        "niah_multi_key": {
          "mean": 0.027777777777777776,
          "std": 0.031823442326082224,
          "vals": [
            0.0,
            0.020833333333333332,
            0.0625
          ]
        },
        "multi_task": {
          "mean": 0.02482269503546099,
          "std": 0.012284048280630334,
          "vals": [
            0.031914893617021274,
            0.010638297872340425,
            0.031914893617021274
          ]
        }
      }
    }
  }
}